in_n_out/__init__.py
in_n_out/_global.py
in_n_out/_store.py
in_n_out/_type_resolution.py
in_n_out/_util.py
in_n_out/py.typed
in_n_out-0.2.0.dist-info/METADATA
in_n_out-0.2.0.dist-info/WHEEL
in_n_out-0.2.0.dist-info/licenses/LICENSE
in_n_out-0.2.0.dist-info/RECORD
