Metadata-Version: 2.3
Name: in-n-out
Version: 0.2.0
Summary: plugable dependency injection and result processing
Project-URL: homepage, https://github.com/pyapp-kit/in-n-out
Project-URL: repository, https://github.com/pyapp-kit/in-n-out
Project-URL: documentations, https://ino.rtfd.io
Author-email: Talley Lambert <talley.lambert@gmail.com>
License: BSD 3-Clause License
License-File: LICENSE
Classifier: Development Status :: 3 - Alpha
Classifier: License :: OSI Approved :: BSD License
Classifier: Programming Language :: Python :: 3
Classifier: Programming Language :: Python :: 3.8
Classifier: Programming Language :: Python :: 3.9
Classifier: Programming Language :: Python :: 3.10
Classifier: Programming Language :: Python :: 3.11
Classifier: Programming Language :: Python :: 3.12
Classifier: Typing :: Typed
Requires-Python: >=3.8
Provides-Extra: dev
Requires-Dist: in-n-out[test]; extra == 'dev'
Requires-Dist: ipython; extra == 'dev'
Requires-Dist: mypy; extra == 'dev'
Requires-Dist: pdbpp; extra == 'dev'
Requires-Dist: pre-commit; extra == 'dev'
Requires-Dist: rich; extra == 'dev'
Requires-Dist: ruff; extra == 'dev'
Provides-Extra: docs
Requires-Dist: mkdocs-gen-files; extra == 'docs'
Requires-Dist: mkdocs-literate-nav; extra == 'docs'
Requires-Dist: mkdocs-material==9.4.1; extra == 'docs'
Requires-Dist: mkdocs==1.5.3; extra == 'docs'
Requires-Dist: mkdocstrings-python==1.7.3; extra == 'docs'
Provides-Extra: test
Requires-Dist: pytest-codspeed; extra == 'test'
Requires-Dist: pytest-cov; extra == 'test'
Requires-Dist: pytest>=6.0; extra == 'test'
Requires-Dist: toolz; extra == 'test'
